AUTHORS.rst
CONTRIBUTING.rst
LICENSE
MANIFEST.in
README.rst
requirements.txt
setup.cfg
setup.py
versioneer.py
datareduction/__init__.py
datareduction/_version.py
datareduction/reduction.py
datareduction/vend.py
datareduction/tests/__init__.py
datareduction/tests/conftest.py
datareduction/tests/test_examples.py
datareduction_stao.egg-info/PKG-INFO
datareduction_stao.egg-info/SOURCES.txt
datareduction_stao.egg-info/dependency_links.txt
datareduction_stao.egg-info/entry_points.txt
datareduction_stao.egg-info/top_level.txt
docs/Makefile
docs/make.bat
docs/source/conf.py
docs/source/index.rst
docs/source/installation.rst
docs/source/min_versions.rst
docs/source/release-history.rst
docs/source/usage.rst