Metadata-Version: 1.2
Name: datareduction-stao
Version: 0.0.1
Summary: Data reduction from databroker to xarray.
Home-page: https://github.com/st3107/datareduction
Author: Songsheng Tao
Author-email: st3107@columbia.edu
License: BSD (3-clause)
Platform: UNKNOWN
Classifier: Development Status :: 2 - Pre-Alpha
Classifier: Natural Language :: English
Classifier: Programming Language :: Python :: 3
Requires-Python: >=3.7
